{"v":"5.5.2","fr":24,"ip":0,"op":72,"w":32,"h":32,"nm":"app_btn_white@2x","ddd":0,"assets":[{"id":"image_0","w":4,"h":32,"u":"images/","p":"img_0.png","e":0}],"layers":[{"ddd":0,"ind":1,"ty":2,"nm":"vol_white2x.png","cl":"png","refId":"image_0","sr":1,"ks":{"o":{"a":0,"k":100,"ix":11},"r":{"a":0,"k":0,"ix":10},"p":{"a":0,"k":[2,15.875,0],"ix":2},"a":{"a":0,"k":[2,16,0],"ix":1},"s":{"a":1,"k":[{"i":{"x":[0.667,0.667,0.667],"y":[1,1,1]},"o":{"x":[0.333,0.333,0.333],"y":[0,0,0]},"t":32,"s":[100,0,100],"e":[100,66,100]},{"i":{"x":[0.667,0.667,0.667],"y":[1,1,1]},"o":{"x":[0.333,0.333,0.333],"y":[0,0,0]},"t":42,"s":[100,66,100],"e":[100,66,100]},{"i":{"x":[0.667,0.667,0.667],"y":[1,1,1]},"o":{"x":[0.333,0.333,0.333],"y":[0,0,0]},"t":46,"s":[100,66,100],"e":[100,0,100]},{"t":56}],"ix":6}},"ao":0,"ip":32,"op":128,"st":32,"bm":0},{"ddd":0,"ind":2,"ty":2,"nm":"vol_white2x.png","cl":"png","refId":"image_0","sr":1,"ks":{"o":{"a":0,"k":100,"ix":11},"r":{"a":0,"k":0,"ix":10},"p":{"a":0,"k":[11.333,15.312,0],"ix":2},"a":{"a":0,"k":[2,16,0],"ix":1},"s":{"a":1,"k":[{"i":{"x":[0.667,0.667,0.667],"y":[1,1,1]},"o":{"x":[0.333,0.333,0.333],"y":[0,0,0]},"t":36,"s":[100,0,100],"e":[100,70,100]},{"i":{"x":[0.667,0.667,0.667],"y":[1,1,1]},"o":{"x":[0.333,0.333,0.333],"y":[0,0,0]},"t":46,"s":[100,70,100],"e":[100,70,100]},{"i":{"x":[0.667,0.667,0.667],"y":[1,1,1]},"o":{"x":[0.333,0.333,0.333],"y":[0,0,0]},"t":50,"s":[100,70,100],"e":[100,0,100]},{"t":60}],"ix":6}},"ao":0,"ip":36,"op":132,"st":36,"bm":0},{"ddd":0,"ind":3,"ty":2,"nm":"vol_white2x.png","cl":"png","refId":"image_0","sr":1,"ks":{"o":{"a":0,"k":100,"ix":11},"r":{"a":0,"k":0,"ix":10},"p":{"a":0,"k":[20.667,15.375,0],"ix":2},"a":{"a":0,"k":[2,16,0],"ix":1},"s":{"a":1,"k":[{"i":{"x":[0.667,0.667,0.667],"y":[1,1,1]},"o":{"x":[0.333,0.333,0.333],"y":[0,0,0]},"t":28,"s":[100,0,100],"e":[100,100,100]},{"i":{"x":[0.667,0.667,0.667],"y":[1,1,1]},"o":{"x":[0.333,0.333,0.333],"y":[0,0,0]},"t":38,"s":[100,100,100],"e":[100,100,100]},{"i":{"x":[0.667,0.667,0.667],"y":[1,1,1]},"o":{"x":[0.333,0.333,0.333],"y":[0,0,0]},"t":42,"s":[100,100,100],"e":[100,0,100]},{"t":52}],"ix":6}},"ao":0,"ip":28,"op":124,"st":28,"bm":0},{"ddd":0,"ind":4,"ty":2,"nm":"vol_white2x.png","cl":"png","refId":"image_0","sr":1,"ks":{"o":{"a":0,"k":100,"ix":11},"r":{"a":0,"k":0,"ix":10},"p":{"a":0,"k":[30,15.375,0],"ix":2},"a":{"a":0,"k":[2,16,0],"ix":1},"s":{"a":1,"k":[{"i":{"x":[0.667,0.667,0.667],"y":[1,1,1]},"o":{"x":[0.333,0.333,0.333],"y":[0,0,0]},"t":36,"s":[100,0,100],"e":[100,48,100]},{"i":{"x":[0.667,0.667,0.667],"y":[1,1,1]},"o":{"x":[0.333,0.333,0.333],"y":[0,0,0]},"t":46,"s":[100,48,100],"e":[100,48,100]},{"i":{"x":[0.667,0.667,0.667],"y":[1,1,1]},"o":{"x":[0.333,0.333,0.333],"y":[0,0,0]},"t":50,"s":[100,48,100],"e":[100,0,100]},{"t":60}],"ix":6}},"ao":0,"ip":36,"op":132,"st":36,"bm":0},{"ddd":0,"ind":5,"ty":2,"nm":"vol_white2x.png","cl":"png","refId":"image_0","sr":1,"ks":{"o":{"a":0,"k":100,"ix":11},"r":{"a":0,"k":0,"ix":10},"p":{"a":0,"k":[30,16,0],"ix":2},"a":{"a":0,"k":[2,16,0],"ix":1},"s":{"a":1,"k":[{"i":{"x":[0.667,0.667,0.667],"y":[1,1,1]},"o":{"x":[0.333,0.333,0.333],"y":[0,0,0]},"t":12,"s":[100,0,100],"e":[100,88,100]},{"i":{"x":[0.667,0.667,0.667],"y":[1,1,1]},"o":{"x":[0.333,0.333,0.333],"y":[0,0,0]},"t":22,"s":[100,88,100],"e":[100,88,100]},{"i":{"x":[0.667,0.667,0.667],"y":[1,1,1]},"o":{"x":[0.333,0.333,0.333],"y":[0,0,0]},"t":26,"s":[100,88,100],"e":[100,0,100]},{"t":36}],"ix":6}},"ao":0,"ip":12,"op":108,"st":12,"bm":0},{"ddd":0,"ind":6,"ty":2,"nm":"vol_white2x.png","cl":"png","refId":"image_0","sr":1,"ks":{"o":{"a":0,"k":100,"ix":11},"r":{"a":0,"k":0,"ix":10},"p":{"a":0,"k":[20.667,15.375,0],"ix":2},"a":{"a":0,"k":[2,16,0],"ix":1},"s":{"a":1,"k":[{"i":{"x":[0.667,0.667,0.667],"y":[1,1,1]},"o":{"x":[0.333,0.333,0.333],"y":[0,0,0]},"t":4,"s":[100,0,100],"e":[100,92,100]},{"i":{"x":[0.667,0.667,0.667],"y":[1,1,1]},"o":{"x":[0.333,0.333,0.333],"y":[0,0,0]},"t":14,"s":[100,92,100],"e":[100,92,100]},{"i":{"x":[0.667,0.667,0.667],"y":[1,1,1]},"o":{"x":[0.333,0.333,0.333],"y":[0,0,0]},"t":18,"s":[100,92,100],"e":[100,0,100]},{"t":28}],"ix":6}},"ao":0,"ip":4,"op":100,"st":4,"bm":0},{"ddd":0,"ind":7,"ty":2,"nm":"vol_white2x.png","cl":"png","refId":"image_0","sr":1,"ks":{"o":{"a":0,"k":100,"ix":11},"r":{"a":0,"k":0,"ix":10},"p":{"a":0,"k":[11.333,15.312,0],"ix":2},"a":{"a":0,"k":[2,16,0],"ix":1},"s":{"a":1,"k":[{"i":{"x":[0.667,0.667,0.667],"y":[1,1,1]},"o":{"x":[0.333,0.333,0.333],"y":[0,0,0]},"t":8,"s":[100,0,100],"e":[100,70,100]},{"i":{"x":[0.667,0.667,0.667],"y":[1,1,1]},"o":{"x":[0.333,0.333,0.333],"y":[0,0,0]},"t":18,"s":[100,70,100],"e":[100,70,100]},{"i":{"x":[0.667,0.667,0.667],"y":[1,1,1]},"o":{"x":[0.333,0.333,0.333],"y":[0,0,0]},"t":22,"s":[100,70,100],"e":[100,0,100]},{"t":32}],"ix":6}},"ao":0,"ip":8,"op":104,"st":8,"bm":0},{"ddd":0,"ind":8,"ty":2,"nm":"vol_white2x.png","cl":"png","refId":"image_0","sr":1,"ks":{"o":{"a":0,"k":100,"ix":11},"r":{"a":0,"k":0,"ix":10},"p":{"a":0,"k":[2,15.875,0],"ix":2},"a":{"a":0,"k":[2,16,0],"ix":1},"s":{"a":1,"k":[{"i":{"x":[0.667,0.667,0.667],"y":[1,1,1]},"o":{"x":[0.333,0.333,0.333],"y":[0,0,0]},"t":0,"s":[100,0,100],"e":[100,90,100]},{"i":{"x":[0.667,0.667,0.667],"y":[1,1,1]},"o":{"x":[0.333,0.333,0.333],"y":[0,0,0]},"t":10,"s":[100,90,100],"e":[100,90,100]},{"i":{"x":[0.667,0.667,0.667],"y":[1,1,1]},"o":{"x":[0.333,0.333,0.333],"y":[0,0,0]},"t":14,"s":[100,90,100],"e":[100,0,100]},{"t":24}],"ix":6}},"ao":0,"ip":0,"op":96,"st":0,"bm":0}],"markers":[]}